Workbook

Sheet Instructions
B2: Portfolio Allocation Tool
B3: Model portfolios, rebalancing, and historical performance in one workbook
B5: How this workbook is organized
B6: 1. Risk Profiles — the target-weight library (Conservative / Balanced / Growth / Aggressive) across Equities, Bonds, Cash and Alternatives. Edit these if your firm uses different model weights.
B7: 2. Model Portfolio Builder — enter a client name, total portfolio value, and risk profile; the sheet looks up the matching target weights and computes the $ allocation for each asset class.
B8: 3. Rebalancing — pulls the target weights/$ from the Model Portfolio Builder and compares them to the client's current holdings (entered by asset class) to show drift and the buy/sell trade needed.
B9: 4. Performance — paste a client's historical valuation snapshots (Date, Portfolio Value) and the sheet computes period returns, cumulative return, CAGR, and annualized volatility, plus a chart.
B11: Color legend
B12: Blue text = your input (edit these cells)
B13: Black text = calculated by formula (do not overwrite)
B14: Green text = a link pulled from another tab (do not overwrite)
B15: Yellow fill = key assumption — check before relying on the output
... B20: • Go to "Performance", replace the sample Date/Value rows with the client's actual historical valuations (same two columns — Date, Portfolio Value). Extend the formulas in columns C–D down if you add rows.

Sheet Risk Profiles
A1: Risk Profile Target Weights
A2: Standard 4-bucket model — edit the blue weights to match your firm's models. Each row must total 100%.
A4: Risk Profile | B4: Equities | C4: Bonds | D4: Cash | E4: Alternatives | F4: Total
A5: Conservative | B5: 0.2 | C5: 0.55 | D5: 0.2 | E5: 0.05 | F5: =SUM(B5:E5) -> 1
A6: Balanced | B6: 0.45 | C6: 0.35 | D6: 0.1 | E6: 0.1 | F6: =SUM(B6:E6) -> 1
A7: Growth | B7: 0.65 | C7: 0.2 | D7: 0.05 | E7: 0.1 | F7: =SUM(B7:E7) -> 1
A8: Aggressive | B8: 0.85 | C8: 0.05 | D8: 0 | E8: 0.1 | F8: =SUM(B8:E8) -> 1
A10: Note: weights are illustrative sample targets provided as a starting template, not investment advice — replace with your firm's approved model weights.

Sheet Model Portfolio Builder
A1: Model Portfolio Builder
A2: Enter the client's details below — target allocation is looked up from the Risk Profiles tab.
A4: Client Name | B4: Jane Sample
A5: Total Portfolio Value ($) | B5: 500000
A6: Risk Profile | B6: Balanced
A8: Asset Class | B8: Target Weight | C8: Target $ Allocation
A9: Equities | B9: =INDEX('Risk Profiles'!$B$5:$B$8,MATCH($B$6,'Risk Profiles'!$A$5:$A$8,0)) -> 0.45 | C9: =B9*$B$5 -> 225000
A10: Bonds | B10: =INDEX('Risk Profiles'!$C$5:$C$8,MATCH($B$6,'Risk Profiles'!$A$5:$A$8,0)) -> 0.35 | C10: =B10*$B$5 -> 175000
A11: Cash | B11: =INDEX('Risk Profiles'!$D$5:$D$8,MATCH($B$6,'Risk Profiles'!$A$5:$A$8,0)) -> 0.1 | C11: =B11*$B$5 -> 50000
A12: Alternatives | B12: =INDEX('Risk Profiles'!$E$5:$E$8,MATCH($B$6,'Risk Profiles'!$A$5:$A$8,0)) -> 0.1 | C12: =B12*$B$5 -> 50000
A13: Total | B13: =SUM(B9:B12) -> 1 | C13: =SUM(C9:C12) -> 500000

Sheet Rebalancing
A1: Rebalancing
A2: Enter the client's current $ value per asset class (blue) to see drift from target and required trades.
A4: Client Name | B4: ='Model Portfolio Builder'!B4 -> Jane Sample
A5: Total Portfolio Value ($) | B5: ='Model Portfolio Builder'!B5 -> 500000
A6: Risk Profile | B6: ='Model Portfolio Builder'!B6 -> Balanced
A8: Asset Class | B8: Target Weight | C8: Target $ | D8: Current $ | E8: Current Weight | F8: Drift $ | G8: Drift % | H8: Action | I8: Trade $
A9: Equities | B9: ='Model Portfolio Builder'!B9 -> 0.45 | C9: ='Model Portfolio Builder'!C9 -> 225000 | D9: 250000 | E9: =IFERROR(D9/SUM($D$9:$D$12),0) -> 0.5 | F9: =D9-C9 -> 25000 | G9: =IFERROR(F9/C9,0) -> 0.11111111 | H9: =IF(F9<0,"Buy",IF(F9>0,"Sell","Hold")) -> Sell | I9: =ABS(F9) -> 25000
A10: Bonds | B10: ='Model Portfolio Builder'!B10 -> 0.35 | C10: ='Model Portfolio Builder'!C10 -> 175000 | D10: 130000 | E10: =IFERROR(D10/SUM($D$9:$D$12),0) -> 0.26 | F10: =D10-C10 -> -45000 | G10: =IFERROR(F10/C10,0) -> -0.25714286 | H10: =IF(F10<0,"Buy",IF(F10>0,"Sell","Hold")) -> Buy | I10: =ABS(F10) -> 45000
A11: Cash | B11: ='Model Portfolio Builder'!B11 -> 0.1 | C11: ='Model Portfolio Builder'!C11 -> 50000 | D11: 90000 | E11: =IFERROR(D11/SUM($D$9:$D$12),0) -> 0.18 | F11: =D11-C11 -> 40000 | G11: =IFERROR(F11/C11,0) -> 0.8 | H11: =IF(F11<0,"Buy",IF(F11>0,"Sell","Hold")) -> Sell | I11: =ABS(F11) -> 40000
A12: Alternatives | B12: ='Model Portfolio Builder'!B12 -> 0.1 | C12: ='Model Portfolio Builder'!C12 -> 50000 | D12: 30000 | E12: =IFERROR(D12/SUM($D$9:$D$12),0) -> 0.06 | F12: =D12-C12 -> -20000 | G12: =IFERROR(F12/C12,0) -> -0.4 | H12: =IF(F12<0,"Buy",IF(F12>0,"Sell","Hold")) -> Buy | I12: =ABS(F12) -> 20000
A13: Total | B13: =SUM(B9:B12) -> 1 | C13: =SUM(C9:C12) -> 500000 | D13: =SUM(D9:D12) -> 500000 | E13: =SUM(E9:E12) -> 1 | F13: =SUM(F9:F12) -> 0 | I13: =SUM(I9:I12) -> 130000
A15: If "Current $" doesn't sum to the Total Portfolio Value, Current Weight is normalized to the sum of the values you entered here; Drift $/% still compares to the Model Portfolio Builder's target $, which is based on Total Portfolio Value.

Sheet Performance
A1: Performance
A2: Replace the sample Date/Portfolio Value rows below with the client's actual historical valuations.
A4: Valuation frequency (periods/year) | C4: 12
A6: Date | B6: Portfolio Value ($) | C6: Period Return % | D6: Cumulative Return % | F6: Summary
A7: 45685 | B7: 500000 | D7: 0 | F7: Start Date | G7: =A7 -> 45685
A8: 45716 | B8: 508500 | C8: =B8/B7-1 -> 0.017 | D8: =B8/$B$7-1 -> 0.017 | F8: End Date | G8: =INDEX(A7:A19,MATCH(MAX(A7:A19),A7:A19,0)) -> 46050
A9: 45744 | B9: 495200 | C9: =B9/B8-1 -> -0.026155359 | D9: =B9/$B$7-1 -> -0.0096 | F9: Start Value | G9: =B7 -> 500000
A10: 45775 | B10: 512800 | C10: =B10/B9-1 -> 0.035541195 | D10: =B10/$B$7-1 -> 0.0256 | F10: End Value | G10: =INDEX(B7:B19,MATCH(MAX(A7:A19),A7:A19,0)) -> 566900
A11: 45805 | B11: 520100 | C11: =B11/B10-1 -> 0.014235569 | D11: =B11/$B$7-1 -> 0.0402 | F11: Total Return % | G11: =G10/G9-1 -> 0.1338
A12: 45836 | B12: 517600 | C12: =B12/B11-1 -> -0.0048067679 | D12: =B12/$B$7-1 -> 0.0352 | F12: Years Elapsed | G12: =(G8-G7)/365.25 -> 0.99931554
A13: 45866 | B13: 531900 | C13: =B13/B12-1 -> 0.027627512 | D13: =B13/$B$7-1 -> 0.0638 | F13: CAGR % | G13: =IFERROR((G10/G9)^(1/G12)-1,"") -> 0.13389752
A14: 45897 | B14: 540200 | C14: =B14/B13-1 -> 0.015604437 | D14: =B14/$B$7-1 -> 0.0804 | F14: Avg Period Return % | G14: =AVERAGE(C8:C19) -> 0.010678141
A15: 45928 | B15: 536700 | C15: =B15/B14-1 -> -0.0064790818 | D15: =B15/$B$7-1 -> 0.0734 | F15: Annualized Volatility % | G15: =STDEV(C8:C19)*SQRT($C$4) -> 0.064547936
A16: 45958 | B16: 549800 | C16: =B16/B15-1 -> 0.024408422 | D16: =B16/$B$7-1 -> 0.0996 | F16: Best Period % | G16: =MAX(C8:C19) -> 0.035541195
A17: 45989 | B17: 558300 | C17: =B17/B16-1 -> 0.015460167 | D17: =B17/$B$7-1 -> 0.1166 | F17: Worst Period % | G17: =MIN(C8:C19) -> -0.026155359
A18: 46019 | B18: 552100 | C18: =B18/B17-1 -> -0.011105141 | D18: =B18/$B$7-1 -> 0.1042
A19: 46050 | B19: 566900 | C19: =B19/B18-1 -> 0.026806738 | D19: =B19/$B$7-1 -> 0.1338
A21: Sample data above is illustrative only — replace rows 7 onward with the client's actual Date / Portfolio Value history (keep the same two columns). Extend the Period Return % and Cumulative Return % formulas down if you add more rows, and update the summary box's row references if the data no longer ends at the row shown.
